flash_select/__init__.py
flash_select/flash_select.py
flash_select-0.0.2.dist-info/METADATA
flash_select-0.0.2.dist-info/WHEEL
flash_select-0.0.2.dist-info/licenses/LICENSE
flash_select-0.0.2.dist-info/RECORD
