Metadata-Version: 2.4
Name: flash-select
Version: 0.0.2
Summary: An extremely fast feature selection algorithm.
Author-email: Miguel Pereira <miguel.b.per@gmail.com>
License-File: LICENSE
Requires-Python: >=3.10
Requires-Dist: numpy>=2.0.0
Requires-Dist: pandas>=2.0.0
Requires-Dist: scipy>=1.0.0
Requires-Dist: shap>=0.47.0
